ops2deb/__init__.py
ops2deb/__main__.py
ops2deb/apt.py
ops2deb/builder.py
ops2deb/cli.py
ops2deb/client.py
ops2deb/delta.py
ops2deb/exceptions.py
ops2deb/extracter.py
ops2deb/fetcher.py
ops2deb/formatter.py
ops2deb/generator.py
ops2deb/jinja.py
ops2deb/lockfile.py
ops2deb/logger.py
ops2deb/parser.py
ops2deb/py.typed
ops2deb/templates.py
ops2deb/updater.py
ops2deb/utils.py
ops2deb-2.7.0.dist-info/LICENSE
ops2deb-2.7.0.dist-info/METADATA
ops2deb-2.7.0.dist-info/WHEEL
ops2deb-2.7.0.dist-info/entry_points.txt
ops2deb-2.7.0.dist-info/RECORD
