Metadata-Version: 2.3
Name: ops2deb
Version: 2.7.0
Summary: Build debian packages
License: MIT
Keywords: Debian,DevOps,Automation,Kubernetes,APT
Author: Upciti
Author-email: support@upciti.com
Requires-Python: >=3.10,<3.12
Classifier: Development Status :: 3 - Alpha
Classifier: Intended Audience :: Developers
Classifier: License :: OSI Approved :: MIT License
Classifier: Programming Language :: Python :: 3
Classifier: Programming Language :: Python :: 3.10
Classifier: Programming Language :: Python :: 3.11
Classifier: Topic :: Software Development :: Code Generators
Classifier: Typing :: Typed
Provides-Extra: pyinstaller
Requires-Dist: Jinja2 (>=3,<4)
Requires-Dist: PyYAML (>=6,<7)
Requires-Dist: aiofiles (>=0.1.9)
Requires-Dist: dirsync (>=2.2.5,<3.0.0)
Requires-Dist: httpx (>=0.20.0)
Requires-Dist: pydantic (>=2,<3)
Requires-Dist: pyinstaller (==6.3.0) ; extra == "pyinstaller"
Requires-Dist: python-debian (>=0.1.42)
Requires-Dist: rich
Requires-Dist: ruamel.yaml (==0.18.14)
Requires-Dist: semver (==3.0.2)
Requires-Dist: typer (>=0.6.1)
Requires-Dist: unix-ar (>=0.2.1,<0.3.0)
Requires-Dist: zstandard
Project-URL: Repository, https://github.com/upciti/ops2deb
